{"cameraMode":{"drawMode":0,"name":"Shaded","section":"Shading Mode"},"sceneLighting":true,"audioPlay":false,"sceneViewState":{"showFog":true,"showMaterialUpdate":false,"showSkybox":true,"showFlares":true,"showImageEffects":true,"showParticleSystems":true},"in2DMode":false,"pivot":{"x":-6.597315788269043,"y":3.8522353172302248,"z":0.4662015736103058},"rotation":{"x":-0.32972341775894167,"y":-0.30641862750053408,"z":0.11390634626150131,"w":-0.8857595920562744},"size":4.1562113761901859,"orthographic":false}